aek_seq_trainer/__init__.py
aek_seq_trainer/trainer.py
aek_seq_trainer/data/__init__.py
aek_seq_trainer/data/dataloader.py
aek_seq_trainer/data/preprocessing.py
aek_seq_trainer/models/__init__.py
aek_seq_trainer/models/lstm.py
aek_seq_trainer/utils/__init__.py
aek_seq_trainer/utils/logger.py
aek_seq_trainer/utils/metrics.py
aek_seq_trainer-0.1.2.dist-info/licenses/LICENSE
aek_seq_trainer-0.1.2.dist-info/METADATA
aek_seq_trainer-0.1.2.dist-info/WHEEL
aek_seq_trainer-0.1.2.dist-info/top_level.txt
aek_seq_trainer-0.1.2.dist-info/RECORD
